<App><Resources /><Sounds /><Materials><Material alpha="1" alphaForSpecular="1" ambientIntensity="0.367347" billboardType="NONE" castShadow="true" cullFaceMode="BACK" diffuse="[0.8,0.00915267,0.634726]" diffuseIntensity="0.8" emitIntensity="0.0" fillMode="SOLID" isTransparent="false" name="Material" receiveShadows="true" renderPass="LIT" shadeless="false" shadowBias="0" shininess="50" specular="[1,1,1]" specularIntensity="0.5" /><Material alpha="1" alphaForSpecular="1" ambientIntensity="0.455782" billboardType="NONE" castShadow="true" cullFaceMode="BACK" diffuse="[0.8,0.778395,0.010701]" diffuseIntensity="0.8" emitIntensity="0.0" fillMode="SOLID" isTransparent="false" name="Material.001" receiveShadows="true" renderPass="LIT" shadeless="false" shadowBias="0" shininess="50" specular="[1,1,1]" specularIntensity="0.5" /><Material alpha="1" alphaForSpecular="1" ambientIntensity="1" billboardType="NONE" castShadow="true" cullFaceMode="BACK" diffuse="[0.8,0.8,0.8]" diffuseIntensity="0.8" emitIntensity="0.0" fillMode="SOLID" isTransparent="false" name="NSGDefault" receiveShadows="true" renderPass="LIT" shadeless="false" shadowBias="0" shininess="50" specular="[1,1,1]" specularIntensity="0.5" /></Materials><Meshes><Mesh name="Cube"><Vertexes><VertexData n="[0,0,-1]" p="[1,1,-1]" /><VertexData n="[0,0,-1]" p="[1,-1,-1]" /><VertexData n="[0,0,-1]" p="[-1,-1,-1]" /><VertexData n="[0,0,-1]" p="[-1,1,-1]" /><VertexData n="[0,-0,1]" p="[1,0.999999,1]" /><VertexData n="[0,-0,1]" p="[-1,1,1]" /><VertexData n="[0,-0,1]" p="[-1,-1,1]" /><VertexData n="[0,-0,1]" p="[0.999999,-1,1]" /><VertexData n="[1,-2.83122e-07,4.47034e-08]" p="[1,1,-1]" /><VertexData n="[1,-2.83122e-07,4.47034e-08]" p="[1,0.999999,1]" /><VertexData n="[1,-2.83122e-07,4.47034e-08]" p="[0.999999,-1,1]" /><VertexData n="[1,-2.83122e-07,4.47034e-08]" p="[1,-1,-1]" /><VertexData n="[-2.83122e-07,-1,-1.04308e-07]" p="[1,-1,-1]" /><VertexData n="[-2.83122e-07,-1,-1.04308e-07]" p="[0.999999,-1,1]" /><VertexData n="[-2.83122e-07,-1,-1.04308e-07]" p="[-1,-1,1]" /><VertexData n="[-2.83122e-07,-1,-1.04308e-07]" p="[-1,-1,-1]" /><VertexData n="[-1,2.23517e-07,-1.3411e-07]" p="[-1,-1,-1]" /><VertexData n="[-1,2.23517e-07,-1.3411e-07]" p="[-1,-1,1]" /><VertexData n="[-1,2.23517e-07,-1.3411e-07]" p="[-1,1,1]" /><VertexData n="[-1,2.23517e-07,-1.3411e-07]" p="[-1,1,-1]" /><VertexData n="[2.38419e-07,1,2.08616e-07]" p="[1,0.999999,1]" /><VertexData n="[2.38419e-07,1,2.08616e-07]" p="[1,1,-1]" /><VertexData n="[2.38419e-07,1,2.08616e-07]" p="[-1,1,-1]" /><VertexData n="[2.38419e-07,1,2.08616e-07]" p="[-1,1,1]" /></Vertexes><Indexes>0 1 2 0 2 3 4 5 6 4 6 7 8 9 10 8 10 11 12 13 14 12 14 15 16 17 18 16 18 19 20 21 22 20 22 23 </Indexes></Mesh><Mesh name="Plane"><Vertexes><VertexData n="[0,0,1]" p="[-1,-1,0]" /><VertexData n="[0,0,1]" p="[1,-1,0]" /><VertexData n="[0,0,1]" p="[1,1,0]" /><VertexData n="[0,0,1]" p="[-1,1,0]" /></Vertexes><Indexes>0 1 2 0 2 3 </Indexes></Mesh></Meshes><Skeletons /><Animations /><Shapes /><Scene ambient="[0.834068,0.078261,0.144595]" enableFog="false" fogDepth="15" fogHeight="0.25" fogMinIntensity="0" fogStart="0.1" horizon="[0.0803424,0.787399,0.200227]" mainCamera="Camera" name="Scene"><SceneNode name="Scene" orientation="[0.707107,-0.707107,-0,-0]"><SceneNode materialName="Material.001" meshName="Plane" name="Plane" position="[0,0,-1]" scale="[10,10,10]"><RigidBody angularDamp="0.1" angularFactor="[1,1,1]" collisionGroup="1" collisionMask="65535" friction="0.5" kinematic="false" linearDamp="0.04" linearFactor="[1,1,1]" mass="0" restitution="0" trigger="false" /></SceneNode><SceneNode materialName="Material" meshName="Cube" name="Cube"><RigidBody angularDamp="0.159" angularFactor="[1,1,1]" collisionGroup="1" collisionMask="255" friction="0.5" kinematic="false" linearDamp="0.0254" linearFactor="[1,1,1]" mass="0" restitution="0" trigger="false" /></SceneNode><SceneNode color="[1,1,1]" diffuse="true" distance="6" energy="3.62" name="Lamp" nodeType="Light" onlyShadow="false" orientation="[0.570948,0.169076,0.272171,0.75588]" position="[-0.130536,0.033268,1.82061]" shadowBias="4" shadowClipEnd="30.002" shadowClipStart="1.0008" shadowColor="[0.000651499,1,0]" shadows="true" specular="true" spotCutOff="75" type="SPOT"><RigidBody angularDamp="0.159" angularFactor="[1,1,1]" collisionGroup="1" collisionMask="255" kinematic="false" linearDamp="0.0254" linearFactor="[1,1,1]" mass="0" trigger="false" /></SceneNode><SceneNode fovy="0.857556" isOrtho="false" name="Camera" nodeType="Camera" orientation="[0.859071,0.419843,-0.124178,-0.265156]" orthoScale="7.31429" position="[-8.25705,-11.8454,9.58346]" sensorFit="0" zFar="100" zNear="0.1"><RigidBody angularDamp="0.625838" angularFactor="[1,1,1]" collisionGroup="1" collisionMask="255" kinematic="false" linearDamp="0.565944" linearFactor="[1,1,1]" mass="0" trigger="false" /></SceneNode></SceneNode><Physics fps="60" gravity="[0,-9.81,0]" maxSubSteps="5" /></Scene></App>